hdl/hw7.sv
module queue(
    input clk,
    input wire [31:0] in,
    input signal,
    output wire [31:0] out,
    output queue_full,
    output queue_empty
);

    reg [31:0] queue [7:0];
    reg full = 0, empty = 1;
    reg [31:0] deqOut;
    integer size = 0;

    always @(posedge clk) begin
        if (signal == 1) begin
            if(size < 8) begin
                queue[size] = in;
                size = size + 1;
                empty = 0;
                if(size == 8) begin
                    full = 1;
                end
            end
        end
        else begin
            if(size > 0) begin
                deqOut = queue[0];
                for (int i = 0; i < size - 1; i = i + 1) begin
                    queue[i] = queue[i + 1];
                end
                size = size - 1;
                full = 0;
                if(size == 0) begin
                    empty = 1;
                end
            end
        end
    end

    assign out = deqOut;
    assign queue_full = full;
    assign queue_empty = empty;

endmodule

hw6.sv
module divider(
	input wire [31:0] dividend,
	input wire [31:0] divisor,
	input clk,
	output wire [31:0] quotient,
	output wire [31:0] remainder
);

	parameter init = 2'b00;
	parameter shift = 2'b01;
	parameter store = 2'b10;

	reg [31:0] q;
	reg [31:0] temp_dividend;
	reg [31:0] i;
	reg [1:0] state = init;

	assign quotient = q;
	assign remainder = temp_dividend;

	always @(posedge clk) begin
		case(state)
			init: begin
				temp_dividend <= 0;
				q <= 0;
				i <= 0;
				state = shift;
			end
			shift: begin
				if(temp_dividend >= divisor) begin
					temp_dividend <= temp_dividend - divisor;
					q <= q + 1;
				end
				else if(i > 31) begin
					state <= store;
				end
				else if (temp_dividend < divisor && i < 32) begin
					temp_dividend[31:0] <= {temp_dividend[30:0], dividend[31 - i]};
					q[31:0] <= {q[30:0], 1'b0};
					i <= i + 1;
					state <= shift;
				end
			end
			store: begin
				state <= store;
			end
		endcase
	end
endmodule

module factorial(
	input wire [31:0] val,
	output wire[31:0] factorial,
	input clk,
	output ready,
	output overflow
);
	parameter init = 2'b00;
	parameter multiply = 2'b01;
	parameter store = 2'b10;

	reg [31:0] counter;
	reg [31:0] ans = 1;
	reg [1:0] state = init;
	reg readyBit = 0;
	reg overflowBit = 0;

	assign overflow = (val > 11) ? 1 : overflowBit;
	assign ready = (val > 11) ? 1 : readyBit;
	assign factorial = (val > 11) ? 0 : ans;

	always @(posedge clk) begin
		case(state)
			init: begin
				readyBit = 0;
				overflowBit = 0;
				counter = val;
				ans = 1;
				state = multiply;
			end
			multiply: begin
				ans = ans * counter;
				counter = counter - 1;
				if(counter > 1) begin
					state = multiply;
				end
				else begin
					state = store;
				end
			end
			store: begin
				readyBit = 1;
				state = store;
			end
		endcase
	end
endmodule

module average(
	input wire [31:0] in,
	input clk,
	output wire [31:0] avg,
	output ready,
	output overflow
);
	localparam init = 2'b00;
	localparam sum = 2'b01;
	localparam store = 2'b10;

	reg [31:0] counter;
	reg [31:0] ans;
	reg state = init;
	reg [31:0] temp;
	reg readyBit;
	reg overflowBit;

	always @(posedge clk) begin
		case(state)
			init: begin
				counter = 0;
				ans = 0;
				temp = 0;
				readyBit = 0;
				overflowBit = 0;
				state = sum;
			end
			sum: begin
				temp = ans + in;
				if(temp < ans || temp < in) begin
					overflowBit = 1;
					ans = 0;
					state = store;
				end
				ans = temp;
				if(counter >= 5) begin
					state = store;
				end
				counter = counter + 1;
			end
			store: begin
				readyBit = 1;
				state = init;
			end
		endcase
	end
	assign avg = ans / 6;
	assign ready = readyBit;
	assign overflow = overflowBit;
endmodule

module stream(
	input wire [31:0] first_stream,
	input wire [31:0] second_stream,
	input clk,
	output wire[31:0] running_sum
);

	reg [31:0] sum = 0;

	always @(posedge clk) begin
		sum <= running_sum;
	end

	assign running_sum = sum + first_stream + second_stream;

endmodule

hw4.sv
module find_max(
    input wire [2:0] a, 
    input wire [2:0] b, 
    input wire [2:0] c, 
    output wire [2:0] max
);
    reg [2:0] maxVal;
    reg [2:0] ans;
    assign maxVal = (a > b) ? ((a > c) ? a : c) : ((b > c) ? b : c);
    always @* begin
        case(maxVal)
            a: ans = 3'b100;
            b: ans = 3'b010;
            c: ans = 3'b001;
        endcase
    end
    assign max = ans;
endmodule

testbench.sv
// MASTER TESTBENCH

module hw4_tb();
// declarations

int test_num;
reg clk;
reg[2:0] a;
reg[2:0] b;
reg[2:0] c;
reg[2:0] expected;
reg [2:0] out;


find_max my_max(.a(a), .b(b), .c(c), .max(out));

initial
begin
    clk = 1'b0;
    forever begin
        # 5 clk = !clk; // forever, toggle the clock every 5 ns
    end
end

initial begin
    $dumpfile ("dump_hw4.vcd");
    $dumpvars (0);
end

initial begin

    integer out_file, expected_file;
    out_file = $fopen("hw4_out_display.text");
    expected_file = $fopen("hw4_expected_display.text");
    
    

    
    // Test 1:
    test_num = 1;
    a        = 3'b101;
    b        = 3'b100;
    c        = 3'b001;
    expected    = 3'b100;
    #10
    
    // Test 2:
    test_num = 2;
    a       = 3'b010;
    b       = 3'b011;
    c       = 3'b000;
    expected = 3'b010;
    #10

    $fclose(out_file);
    $fclose(expected_file);

    // $finish;


end // initial

 // clock toggles after every 5 ns.
initial 
begin
    integer out_file, expected_file;
    out_file = $fopen("hw4_out_display.text");
    expected_file = $fopen("hw4_expected_display.text");
    // clk = 1'b0;
    forever begin
        @(posedge clk) begin
            $display ("%t, out =  %b, expected = %b", $time, out, expected);
            $fwrite(out_file, "%t, out = %b\n", $time, out);
            $fwrite(expected_file, "%t, out = %b\n", $time, expected);
        end
    end
    $fclose(out_file);
    $fclose(expected_file);
end //initial  
endmodule

module hw6q1_tb();
// declarations

int test_num;
reg clk;
reg[31:0] numerator;
reg[31:0] denominator;
reg [31:0] quotient;
reg [31:0] remainder;
reg [31:0] expected_quotient;
reg [31:0] expected_remainder;
reg [8:0] cycle_counter = 0;

divider my_divider(.dividend(numerator), .divisor(denominator), .clk(clk), .quotient(quotient), .remainder(remainder));

initial
begin
    clk = 1'b0;
    forever begin
        # 5 clk = !clk; // forever, toggle the clock every 5 ns - so 1 clock cycle is 10 ms
    end
end

initial begin
    $dumpfile ("dump_hw6q1.vcd");
    $dumpvars (0);
end

initial begin
    // Test 1:
    numerator = 9;
    denominator = 2;
    expected_quotient = 4;
    expected_remainder = 1;
    // Test 2:
    #640
    numerator = 30;
    denominator = 4;
    expected_quotient = 7;
    expected_remainder = 2;
    #640 // wait 32 cycles

    $finish;

end // initial

 // clock toggles after every 5 ns.
initial 
begin
    integer out_file, expected_file, debug_file;
    out_file = $fopen("hw6q1_out_display.text");
    expected_file = $fopen("hw6q1_expected_display.text");
    debug_file = $fopen("dbg.text");
    // clk = 1'b0;
    forever begin
        @(posedge clk) begin
            cycle_counter <= cycle_counter + 1;
            $fwrite(debug_file, "cycle_counter = %b\n", cycle_counter); 
            if (cycle_counter == 31 || cycle_counter == 63) begin    
                $fwrite(out_file, "cycle_counter = %b\n", cycle_counter);
                $fwrite(expected_file, "cycle_counter = %b\n", cycle_counter);
                $display ("%t, quotient =  %b, remainder = %b, expected quotient = %b, expected remainder = %b", $time, quotient, remainder, expected_quotient, expected_remainder);
                $fwrite(out_file, "%t, quotient = %b\n, remainder = %b\n", $time, quotient, remainder);
                $fwrite(expected_file, "%t, quotient = %b\n, remainder = %b\n", $time, expected_quotient, expected_remainder);
            end
        end
    end
    $fclose(out_file);
    $fclose(expected_file);
    $fclose(debug_file);
end //initial  
endmodule

module hw6q2_tb();

// declarations
reg [31:0] val;
reg clk;

reg [31:0] fact;
reg overflow;
reg [31:0] expected_fact;
reg expected_overflow;
reg ready;
reg [8:0] cycle_counter = 0;


factorial my_fact(val, fact, clk, ready, overflow);

initial begin
    clk = 1'b0;
    forever begin
        # 5 clk = ~clk;
    end
end


initial begin
    $dumpfile ("dump_hw6q2.vcd");
    $dumpvars (0);
end

initial begin



    integer out_file, expected_file;
    out_file = $fopen("hw6q2_out_display.text");
    expected_file = $fopen("hw6q2_expected_display.text");
    
    

    
    // Test 1:
    val = 5;
    expected_fact = 120;
    expected_overflow = 0;
    #100
    
    // Test 2:
    val = 50;
    expected_fact = 0;
    expected_overflow = 1;
    #100

    $fclose(out_file);
    $fclose(expected_file);



end // initial

 // clock toggles after every 5 ns.
initial 
begin
    integer out_file, expected_file, debug_file;
    out_file = $fopen("hw6q2_out_display.text");
    expected_file = $fopen("hw6q2_expected_display.text");
    debug_file = $fopen("dbg.text");
    // clk = 1'b0;
    forever begin
        @(posedge clk) begin
            cycle_counter <= cycle_counter + 1;
            $fwrite(debug_file, "cycle_counter = %b\n", cycle_counter); 
            if (ready == 1) begin    
                $fwrite(out_file, "cycle_counter = %b\n", cycle_counter);
                $fwrite(expected_file, "cycle_counter = %b\n", cycle_counter);
                $display ("%t, factorial =  %b, overflow = %b, expected factorial = %b, expected overflow = %b", $time, fact, overflow, expected_fact, expected_overflow);

                $fwrite(out_file, "%t, input = %b\n", $time, val);
                $fwrite(expected_file, "%t, input = %b\n", $time, val);
                $fwrite(out_file, "%t, factorial = %b\n, overflow = %b\n", $time, fact, overflow);
                $fwrite(expected_file, "%t, factorial = %b\n, overflow = %b\n", $time, expected_fact, expected_overflow);
            end
        end
    end
    $fclose(out_file);
    $fclose(expected_file);
    $fclose(debug_file);
end //initial  
endmodule

module hw6q3tb();

reg [31:0] in;
// keep store inputs ahead of time for testing
reg [31:0] input_1;
reg [31:0] input_2;
reg [31:0] input_3;
reg [31:0] input_4;
reg [31:0] input_5;
reg [31:0] input_6;

reg clk = 0;
reg ready;

reg [31:0] avg;
reg overflow;
reg [31:0] expected_avg = 0;
reg expected_overflow = 0;

reg [8:0] cycle_counter = 0;

average my_avg(in, clk, avg, ready, overflow);


initial begin
    clk = 1'b0;
    forever begin
        # 5 clk = ~clk;
    end
end


initial begin
    $dumpfile ("dump_hw6q3.vcd");
    $dumpvars (0);
end

initial begin


    integer out_file, expected_file;
    out_file = $fopen("hw6q3_out_display.text");
    expected_file = $fopen("hw6q3_expected_display.text");
    
    in = 0;

    
    // Test 1:
    input_1 = 2;
    input_2 = 4;
    input_3 = 6;
    input_4 = 8;
    input_5 = 10;
    input_6 = 12;
    #10
    in = input_1;
    #10
    in = input_2;
    #10
    in = input_3;
    #10
    in = input_4;
    #10
    in = input_5;
    #10
    in = input_6;
    expected_avg = 7;
    expected_overflow = 0;
    #10
    
    // Test 2:
    input_1 = {1'b1, 31'b0};
    input_2 = {1'b1, 31'b0};
    input_3 = {1'b1, 31'b0};
    input_4 = {1'b1, 31'b0};
    input_5 = {1'b1, 31'b0};
    input_6 = {1'b1, 31'b0};
    in = input_1;
    #10
    in = input_2;
    #10
    in = input_3;
    #10
    in = input_4;
    #10
    in = input_5;
    #10
    in = input_6;
    expected_avg = 0;
    expected_overflow = 1;
    #10

    $fclose(out_file);
    $fclose(expected_file);

end


 // clock toggles after every 5 ns.
initial 
begin
    integer out_file, expected_file, debug_file;
    out_file = $fopen("hw6q3_out_display.text");
    expected_file = $fopen("hw6q3_expected_display.text");
    debug_file = $fopen("dbg.text");
    // clk = 1'b0;
    forever begin
        @(posedge clk) begin
            cycle_counter <= cycle_counter + 1;
            $fwrite(debug_file, "cycle_counter = %d\n", cycle_counter); 
            if (ready == 1) begin    
                $fwrite(out_file, "cycle_counter = %d\n", cycle_counter);
                $fwrite(expected_file, "cycle_counter = %d\n", cycle_counter);
                $display ("%t, avg =  %b, overflow = %b, expected avg = %b, expected overflow = %b", $time, avg, overflow, expected_avg, expected_overflow);

                $fwrite(out_file, "%t, input_1 = \t%d\n", $time, input_1);
                $fwrite(out_file, "%t, input_2 = \t%d\n", $time, input_2);
                $fwrite(out_file, "%t, input_3 = \t%d\n", $time, input_3);
                $fwrite(out_file, "%t, input_4 = \t%d\n", $time, input_4);
                $fwrite(out_file, "%t, input_5 = \t%d\n", $time, input_5);
                $fwrite(out_file, "%t, input_6 = \t%d\n", $time, input_6);
                $fwrite(out_file, "%t, average = \t%d\n", $time, avg);
                $fwrite(out_file, "%t, overflow = \t%d\n", $time, overflow);

                $fwrite(expected_file, "%t, input_1 = \t%d\n", $time, input_1);
                $fwrite(expected_file, "%t, input_2 = \t%d\n", $time, input_2);
                $fwrite(expected_file, "%t, input_3 = \t%d\n", $time, input_3);
                $fwrite(expected_file, "%t, input_4 = \t%d\n", $time, input_4);
                $fwrite(expected_file, "%t, input_5 = \t%d\n", $time, input_5);
                $fwrite(expected_file, "%t, input_6 = \t%d\n", $time, input_6);
                $fwrite(expected_file, "%t, average = \t%d\n", $time, expected_avg);
                $fwrite(expected_file, "%t, overflow = \t%d\n", $time, expected_overflow);
            end
        end
    end
    $fclose(out_file);
    $fclose(expected_file);
    $fclose(debug_file);
end //initial  


endmodule

module hw6q4tb();

reg [31:0] stream_1;
reg [31:0] stream_2;

reg [31:0] expected_sum;

reg clk = 0;

reg [31:0] running_sum;

stream my_stream(stream_1, stream_2, clk, running_sum);

initial begin
    clk = 1'b0;
    forever begin
        # 5 clk = ~clk;
    end
end


initial begin
    $dumpfile ("dump_hw6q4.vcd");
    $dumpvars (0);
end

initial begin


    integer out_file, expected_file;
    out_file = $fopen("hw6q4_out_display.text");
    expected_file = $fopen("hw6q4_expected_display.text");
        
    // Test 1:
    stream_1 = 2;
    stream_2 = 4;
    expected_sum = 6;
    #10
    stream_1 = 3;
    stream_2 = 5;
    expected_sum = 14;
    #10
    stream_1 = 4;
    stream_2 = 6;
    expected_sum = 24;
    #10
    stream_1 = 0;
    stream_2 = 0; // so expected matches actual


    $fclose(out_file);
    $fclose(expected_file);

end


 // clock toggles after every 5 ns.
initial 
begin
    integer out_file, expected_file, debug_file;
    out_file = $fopen("hw6q4_out_display.text");
    expected_file = $fopen("hw6q4_expected_display.text");
    debug_file = $fopen("dbg.text");
    // clk = 1'b0;
    forever begin
        @(posedge clk) begin
                $display ("%t, sum =  %b, expected sum = %b", $time, running_sum, expected_sum);
                
                $fwrite(out_file, "%t, stream1 = \t%d\n", $time, stream_1);
                $fwrite(out_file, "%t, stream2 = \t%d\n", $time, stream_2);
                $fwrite(out_file, "%t, sum = \t%d\n", $time, running_sum);

                $fwrite(expected_file, "%t, stream1 = \t%d\n", $time, stream_1);
                $fwrite(expected_file, "%t, stream2 = \t%d\n", $time, stream_2);
                $fwrite(expected_file, "%t, sum = \t%d\n", $time, expected_sum);
        end
    end
    $fclose(out_file);
    $fclose(expected_file);
    $fclose(debug_file);
end //initial  


endmodule

dump_hw4.vcd
$date
	Sat Apr 13 00:11:16 2024
$end
$version
	Icarus Verilog
$end
$timescale
	1s
$end
$scope module hw4_tb $end
$var wire 3 ! out [2:0] $end
$var reg 3 " a [2:0] $end
$var reg 3 # b [2:0] $end
$var reg 3 $ c [2:0] $end
$var reg 1 % clk $end
$var reg 3 & expected [2:0] $end
$var integer 32 ' test_num [31:0] $end
$scope module my_max $end
$var wire 3 ( a [2:0] $end
$var wire 3 ) b [2:0] $end
$var wire 3 * c [2:0] $end
$var wire 3 + max [2:0] $end
$var wire 3 , maxVal [2:0] $end
$var reg 3 - ans [2:0] $end
$upscope $end
$scope begin $unm_blk_4 $end
$var integer 32 . expected_file [31:0] $end
$var integer 32 / out_file [31:0] $end
$upscope $end
$scope begin $unm_blk_5 $end
$var integer 32 0 expected_file [31:0] $end
$var integer 32 1 out_file [31:0] $end
$upscope $end
$upscope $end
$scope module hw6q1_tb $end
$var wire 32 2 remainder [31:0] $end
$var wire 32 3 quotient [31:0] $end
$var reg 1 4 clk $end
$var reg 9 5 cycle_counter [8:0] $end
$var reg 32 6 denominator [31:0] $end
$var reg 32 7 expected_quotient [31:0] $end
$var reg 32 8 expected_remainder [31:0] $end
$var reg 32 9 numerator [31:0] $end
$scope module my_divider $end
$var wire 1 4 clk $end
$var wire 32 : dividend [31:0] $end
$var wire 32 ; divisor [31:0] $end
$var wire 32 < quotient [31:0] $end
$var wire 32 = remainder [31:0] $end
$var reg 32 > i [31:0] $end
$var reg 32 ? q [31:0] $end
$var reg 2 @ state [1:0] $end
$var reg 32 A temp_dividend [31:0] $end
$upscope $end
$scope begin $unm_blk_12 $end
$var integer 32 B debug_file [31:0] $end
$var integer 32 C expected_file [31:0] $end
$var integer 32 D out_file [31:0] $end
$upscope $end
$upscope $end
$scope module hw6q2_tb $end
$var wire 1 E ready $end
$var wire 1 F overflow $end
$var wire 32 G fact [31:0] $end
$var reg 1 H clk $end
$var reg 9 I cycle_counter [8:0] $end
$var reg 32 J expected_fact [31:0] $end
$var reg 1 K expected_overflow $end
$var reg 32 L val [31:0] $end
$scope module my_fact $end
$var wire 1 H clk $end
$var wire 32 M val [31:0] $end
$var wire 1 E ready $end
$var wire 1 F overflow $end
$var wire 32 N factorial [31:0] $end
$var reg 32 O ans [31:0] $end
$var reg 32 P counter [31:0] $end
$var reg 1 Q overflowBit $end
$var reg 1 R readyBit $end
$var reg 2 S state [1:0] $end
$upscope $end
$scope begin $unm_blk_19 $end
$var integer 32 T expected_file [31:0] $end
$var integer 32 U out_file [31:0] $end
$upscope $end
$scope begin $unm_blk_20 $end
$var integer 32 V debug_file [31:0] $end
$var integer 32 W expected_file [31:0] $end
$var integer 32 X out_file [31:0] $end
$upscope $end
$upscope $end
$scope module hw6q3tb $end
$var wire 1 Y ready $end
$var wire 1 Z overflow $end
$var wire 32 [ avg [31:0] $end
$var reg 1 \ clk $end
$var reg 9 ] cycle_counter [8:0] $end
$var reg 32 ^ expected_avg [31:0] $end
$var reg 1 _ expected_overflow $end
$var reg 32 ` in [31:0] $end
$var reg 32 a input_1 [31:0] $end
$var reg 32 b input_2 [31:0] $end
$var reg 32 c input_3 [31:0] $end
$var reg 32 d input_4 [31:0] $end
$var reg 32 e input_5 [31:0] $end
$var reg 32 f input_6 [31:0] $end
$scope module my_avg $end
$var wire 1 \ clk $end
$var wire 32 g in [31:0] $end
$var wire 1 Z overflow $end
$var wire 1 Y ready $end
$var wire 32 h avg [31:0] $end
$var reg 32 i ans [31:0] $end
$var reg 32 j counter [31:0] $end
$var reg 1 k overflowBit $end
$var reg 1 l readyBit $end
$var reg 1 m state $end
$var reg 32 n temp [31:0] $end
$upscope $end
$scope begin $unm_blk_27 $end
$var integer 32 o expected_file [31:0] $end
$var integer 32 p out_file [31:0] $end
$upscope $end
$scope begin $unm_blk_28 $end
$var integer 32 q debug_file [31:0] $end
$var integer 32 r expected_file [31:0] $end
$var integer 32 s out_file [31:0] $end
$upscope $end
$upscope $end
$scope module hw6q4tb $end
$var wire 32 t running_sum [31:0] $end
$var reg 1 u clk $end
$var reg 32 v expected_sum [31:0] $end
$var reg 32 w stream_1 [31:0] $end
$var reg 32 x stream_2 [31:0] $end
$scope module my_stream $end
$var wire 1 u clk $end
$var wire 32 y first_stream [31:0] $end
$var wire 32 z second_stream [31:0] $end
$var wire 32 { running_sum [31:0] $end
$var reg 32 | sum [31:0] $end
$upscope $end
$scope begin $unm_blk_35 $end
$var integer 32 } expected_file [31:0] $end
$var integer 32 ~ out_file [31:0] $end
$upscope $end
$scope begin $unm_blk_36 $end
$var integer 32 !" debug_file [31:0] $end
$var integer 32 "" expected_file [31:0] $end
$var integer 32 #" out_file [31:0] $end
$upscope $end
$upscope $end
$scope module queue $end
$var wire 1 $" clk $end
$var wire 32 %" in [31:0] $end
$var wire 32 &" out [31:0] $end
$var wire 1 '" queue_empty $end
$var wire 1 (" queue_full $end
$var wire 1 )" signal $end
$var reg 32 *" deqOut [31:0] $end
$var reg 1 +" empty $end
$var reg 1 ," full $end
$var integer 32 -" size [31:0] $end
$scope begin $ivl_for_loop0 $end
$var integer 32 ." i [31:0] $end
$upscope $end
$upscope $end
$scope module hw4_tb $end
$scope module my_max $end
$upscope $end
$scope begin $unm_blk_4 $end
$upscope $end
$scope begin $unm_blk_5 $end
$upscope $end
$upscope $end
$scope module hw6q1_tb $end
$scope module my_divider $end
$upscope $end
$scope begin $unm_blk_12 $end
$upscope $end
$upscope $end
$scope module hw6q2_tb $end
$scope module my_fact $end
$upscope $end
$scope begin $unm_blk_19 $end
$upscope $end
$scope begin $unm_blk_20 $end
$upscope $end
$upscope $end
$scope module hw6q3tb $end
$scope module my_avg $end
$upscope $end
$scope begin $unm_blk_27 $end
$upscope $end
$scope begin $unm_blk_28 $end
$upscope $end
$upscope $end
$scope module hw6q4tb $end
$scope module my_stream $end
$upscope $end
$scope begin $unm_blk_35 $end
$upscope $end
$scope begin $unm_blk_36 $end
$upscope $end
$upscope $end
$scope module queue $end
$scope begin $ivl_for_loop0 $end
$upscope $end
$upscope $end
$scope module hw4_tb $end
$scope module my_max $end
$upscope $end
$scope begin $unm_blk_4 $end
$upscope $end
$scope begin $unm_blk_5 $end
$upscope $end
$upscope $end
$scope module hw6q1_tb $end
$scope module my_divider $end
$upscope $end
$scope begin $unm_blk_12 $end
$upscope $end
$upscope $end
$scope module hw6q2_tb $end
$scope module my_fact $end
$upscope $end
$scope begin $unm_blk_19 $end
$upscope $end
$scope begin $unm_blk_20 $end
$upscope $end
$upscope $end
$scope module hw6q3tb $end
$scope module my_avg $end
$upscope $end
$scope begin $unm_blk_27 $end
$upscope $end
$scope begin $unm_blk_28 $end
$upscope $end
$upscope $end
$scope module hw6q4tb $end
$scope module my_stream $end
$upscope $end
$scope begin $unm_blk_35 $end
$upscope $end
$scope begin $unm_blk_36 $end
$upscope $end
$upscope $end
$scope module queue $end
$scope begin $ivl_for_loop0 $end
$upscope $end
$upscope $end
$scope module hw4_tb $end
$scope module my_max $end
$upscope $end
$scope begin $unm_blk_4 $end
$upscope $end
$scope begin $unm_blk_5 $end
$upscope $end
$upscope $end
$scope module hw6q1_tb $end
$scope module my_divider $end
$upscope $end
$scope begin $unm_blk_12 $end
$upscope $end
$upscope $end
$scope module hw6q2_tb $end
$scope module my_fact $end
$upscope $end
$scope begin $unm_blk_19 $end
$upscope $end
$scope begin $unm_blk_20 $end
$upscope $end
$upscope $end
$scope module hw6q3tb $end
$scope module my_avg $end
$upscope $end
$scope begin $unm_blk_27 $end
$upscope $end
$scope begin $unm_blk_28 $end
$upscope $end
$upscope $end
$scope module hw6q4tb $end
$scope module my_stream $end
$upscope $end
$scope begin $unm_blk_35 $end
$upscope $end
$scope begin $unm_blk_36 $end
$upscope $end
$upscope $end
$scope module queue $end
$scope begin $ivl_for_loop0 $end
$upscope $end
$upscope $end
$scope module hw4_tb $end
$scope module my_max $end
$upscope $end
$scope begin $unm_blk_4 $end
$upscope $end
$scope begin $unm_blk_5 $end
$upscope $end
$upscope $end
$scope module hw6q1_tb $end
$scope module my_divider $end
$upscope $end
$scope begin $unm_blk_12 $end
$upscope $end
$upscope $end
$scope module hw6q2_tb $end
$scope module my_fact $end
$upscope $end
$scope begin $unm_blk_19 $end
$upscope $end
$scope begin $unm_blk_20 $end
$upscope $end
$upscope $end
$scope module hw6q3tb $end
$scope module my_avg $end
$upscope $end
$scope begin $unm_blk_27 $end
$upscope $end
$scope begin $unm_blk_28 $end
$upscope $end
$upscope $end
$scope module hw6q4tb $end
$scope module my_stream $end
$upscope $end
$scope begin $unm_blk_35 $end
$upscope $end
$scope begin $unm_blk_36 $end
$upscope $end
$upscope $end
$scope module queue $end
$scope begin $ivl_for_loop0 $end
$upscope $end
$upscope $end
$enddefinitions $end
#0
$dumpvars
b0 ."
b0 -"
0,"
1+"
bx *"
z)"
0("
1'"
bx &"
bz %"
z$"
b100000000000000000000 #"
b1000000000000000000000 ""
b10000000000000000000000 !"
b1000000000000000000 ~
b10000000000000000000 }
b0 |
b110 {
b100 z
b10 y
b100 x
b10 w
b110 v
0u
b110 t
b1000000000000000 s
b10000000000000000 r
b100000000000000000 q
b10000000000000 p
b100000000000000 o
bx n
0m
xl
xk
bx j
bx i
bx h
b0 g
b1100 f
b1010 e
b1000 d
b110 c
b100 b
b10 a
b0 `
0_
b0 ^
b0 ]
0\
bx [
xZ
xY
b10000000000 X
b100000000000 W
b1000000000000 V
b100000000 U
b1000000000 T
b0 S
0R
0Q
bx P
b1 O
b1 N
b101 M
b101 L
0K
b1111000 J
b0 I
0H
b1 G
0F
0E
b100000 D
b1000000 C
b10000000 B
bx A
b0 @
bx ?
bx >
bx =
bx <
b10 ;
b1001 :
b1001 9
b1 8
b100 7
b10 6
b0 5
04
bx 3
bx 2
b1000 1
b10000 0
b10 /
b100 .
b100 -
b101 ,
b100 +
b1 *
b100 )
b101 (
b1 '
b100 &
0%
b1 $
b100 #
b101 "
b100 !
$end
#5
b1100 t
b1100 {
b110 |
b1 ]
b1 I
b0 >
b0 3
b0 <
b0 ?
b0 2
b0 =
b0 A
b1 5
1m
0Z
0k
0Y
0l
b0 n
b0 [
b0 h
b0 i
b0 j
b1 S
b101 P
b1 @
1u
1\
1H
14
1%
#10
b10 !
b10 +
b10 -
b11 ,
0u
0\
0H
04
0%
b1110 v
b101 x
b101 z
b1110 t
b1110 {
b11 w
b11 y
b10 `
b10 g
b10 &
b0 $
b0 *
b11 #
b11 )
b10 "
b10 (
b10 '
#15
b10110 t
b10110 {
b1110 |
b10 ]
b10 I
b10 5
b1 >
b101 G
b101 N
b1 j
b10 i
b10 n
b100 P
b101 O
1u
1\
1H
14
1%
#20
0u
0\
0H
04
0%
b11000 v
b110 x
b110 z
b11000 t
b11000 {
b100 w
b100 y
b100 `
b100 g
#25
b100010 t
b100010 {
b11000 |
b11 ]
b11 I
b10 >
b11 5
b10100 G
b10100 N
b10 j
b1 [
b1 h
b110 i
b110 n
b11 P
b10100 O
1u
1\
1H
14
1%
#30
0u
0\
0H
04
0%
b0 x
b0 z
b11000 t
b11000 {
b0 w
b0 y
b110 `
b110 g
#35
b100 ]
b100 I
b100 5
b11 >
b111100 G
b111100 N
b11 j
b10 [
b10 h
b1100 i
b1100 n
b10 P
b111100 O
1u
1\
1H
14
1%
#40
0u
0\
0H
04
0%
b1000 `
b1000 g
#45
b101 ]
b101 I
b100 >
b101 5
b1111000 G
b1111000 N
b100 j
b11 [
b11 h
b10100 i
b10100 n
b10 S
b1 P
b1111000 O
1u
1\
1H
14
1%
#50
0u
0\
0H
04
0%
b1010 `
b1010 g
#55
b110 ]
b110 I
b110 5
b101 >
1E
b101 j
b101 [
b101 h
b11110 i
b11110 n
1R
1u
1\
1H
14
1%
#60
0u
0\
0H
04
0%
b111 ^
b1100 `
b1100 g
#65
b111 ]
b111 I
b110 >
b111 5
b110 j
0m
b111 [
b111 h
b101010 i
b101010 n
1u
1\
1H
14
1%
#70
0u
0\
0H
04
0%
b10000000000000000000000000000000 `
b10000000000000000000000000000000 g
b10000000000000000000000000000000 f
b10000000000000000000000000000000 e
b10000000000000000000000000000000 d
b10000000000000000000000000000000 c
b10000000000000000000000000000000 b
b10000000000000000000000000000000 a
#75
b1000 ]
b1000 I
b1000 5
b111 >
1m
b0 n
b0 [
b0 h
b0 i
b0 j
1u
1\
1H
14
1%
#80
0u
0\
0H
04
0%
#85
b1001 ]
b1001 I
b1000 >
b1001 5
b1 j
b10101010101010101010101010101 [
b10101010101010101010101010101 h
b10000000000000000000000000000000 i
b10000000000000000000000000000000 n
1u
1\
1H
14
1%
#90
0u
0\
0H
04
0%
#95
b1010 ]
b1010 I
b1010 5
b1001 >
b10 j
0m
b0 [
b0 h
b0 i
1Z
1k
b0 n
1u
1\
1H
14
1%
#100
1F
b0 G
b0 N
0u
0\
0H
04
0%
1K
b0 J
b110010 L
b110010 M
#105
b1011 ]
b1011 I
b1010 >
b1011 5
1m
0Z
0k
b0 j
1u
1\
1H
14
1%
#110
0u
0\
0H
04
0%
#115
b1100 ]
b1100 I
b1100 5
b1011 >
b1 j
b10101010101010101010101010101 [
b10101010101010101010101010101 h
b10000000000000000000000000000000 i
b10000000000000000000000000000000 n
1u
1\
1H
14
1%
#120
0u
0\
0H
04
0%
1_
b0 ^
#125
b1101 ]
b1101 I
b1100 >
b1101 5
b10 j
0m
b0 [
b0 h
b0 i
1Z
1k
b0 n
1u
1\
1H
14
1%
#130
0u
0\
0H
04
0%
#135
b1110 ]
b1110 I
b1110 5
b1101 >
1m
0Z
0k
b0 j
1u
1\
1H
14
1%
#140
0u
0\
0H
04
0%
#145
b1111 ]
b1111 I
b1110 >
b1111 5
b1 j
b10101010101010101010101010101 [
b10101010101010101010101010101 h
b10000000000000000000000000000000 i
b10000000000000000000000000000000 n
1u
1\
1H
14
1%
#150
0u
0\
0H
04
0%
#155
b10000 ]
b10000 I
b10000 5
b1111 >
b10 j
0m
b0 [
b0 h
b0 i
1Z
1k
b0 n
1u
1\
1H
14
1%
#160
0u
0\
0H
04
0%
#165
b10001 ]
b10001 I
b10000 >
b10001 5
1m
0Z
0k
b0 j
1u
1\
1H
14
1%
#170
0u
0\
0H
04
0%
#175
b10010 ]
b10010 I
b10010 5
b10001 >
b1 j
b10101010101010101010101010101 [
b10101010101010101010101010101 h
b10000000000000000000000000000000 i
b10000000000000000000000000000000 n
1u
1\
1H
14
1%
#180
0u
0\
0H
04
0%
#185
b10011 ]
b10011 I
b10010 >
b10011 5
b10 j
0m
b0 [
b0 h
b0 i
1Z
1k
b0 n
1u
1\
1H
14
1%
#190
0u
0\
0H
04
0%
#195
b10100 ]
b10100 I
b10100 5
b10011 >
1m
0Z
0k
b0 j
1u
1\
1H
14
1%
#200
0u
0\
0H
04
0%
#205
b10101 ]
b10101 I
b10100 >
b10101 5
b1 j
b10101010101010101010101010101 [
b10101010101010101010101010101 h
b10000000000000000000000000000000 i
b10000000000000000000000000000000 n
1u
1\
1H
14
1%
#210
0u
0\
0H
04
0%
#215
b10110 ]
b10110 I
b10110 5
b10101 >
b10 j
0m
b0 [
b0 h
b0 i
1Z
1k
b0 n
1u
1\
1H
14
1%
#220
0u
0\
0H
04
0%
#225
b10111 ]
b10111 I
b10110 >
b10111 5
1m
0Z
0k
b0 j
1u
1\
1H
14
1%
#230
0u
0\
0H
04
0%
